Metadata-Version: 2.1
Name: quick-knn
Version: 0.1.3
Summary: LSH for Jaccard and Cosine Similarity
Home-page: https://github.com/blester125/quick_knn
Author: blester125
Author-email: blester125@gmail.com
License: MIT
Download-URL: https://github.com/blester125/quick_knn/archive/0.1.3.tar.gz
Keywords: Data Mining
Platform: UNKNOWN
Classifier: Programming Language :: Python :: 3 :: Only
Classifier: Intended Audience :: Developers
Classifier: Natural Language :: English
Classifier: Intended Audience :: Science/Research
Classifier: License :: OSI Approved :: MIT License
Classifier: Environment :: Console
Classifier: Development Status :: 3 - Alpha
Classifier: Topic :: Scientific/Engineering
Requires-Python: >=3.6
